{
  "id": "badr",
  "slug": "badr",
  "title": "بادر",
  "category": "الحملات والتواصل",
  "icon": "campaign",
  "status": "open",
  "description": "مشروع لتأهيل الشباب على تصميم وتنفيذ حملات مجتمعية احترافية ذات أثر مجتمعي ملموس.",
  "longDescription": "مشروع بادر يُؤهّل الشباب لقيادة حملات مجتمعية مؤثرة من خلال تطوير مهاراتهم في التواصل والإقناع والتسويق الاجتماعي. يشمل المشروع ورش تدريبية عملية وتنفيذ حملات ميدانية حقيقية، مع توثيق وقياس أثرها المجتمعي لضمان الجودة والاستمرارية.",
  "vision": "شباب قادر على قيادة حملات مؤثرة تُحدث تغييراً إيجابياً في المجتمع.",
  "mission": "تأهيل وتوجيه الشباب لتصميم وتنفيذ حملات احترافية ذات أثر مجتمعي ملموس.",
  "objectives": [
    "تصميم وتنفيذ حملات مجتمعية ذات أثر ملموس في المحيط المحلي",
    "تدريب الشباب على مهارات التواصل والإقناع والتسويق الاجتماعي",
    "إطلاق مبادرات ميدانية تخدم الشرائح المستهدفة في المجتمع",
    "بناء قدرات الشباب في الاتصال المؤسسي وإدارة الحملات",
    "توثيق وقياس أثر الحملات المجتمعية المنفذة وتقييم نتائجها"
  ]
}
